LICENSE
MANIFEST.in
README.md
setup.cfg
setup.py
tap_frontapp/__init__.py
tap_frontapp/context.py
tap_frontapp/http.py
tap_frontapp/schemas.py
tap_frontapp/streams.py
tap_frontapp.egg-info/PKG-INFO
tap_frontapp.egg-info/SOURCES.txt
tap_frontapp.egg-info/dependency_links.txt
tap_frontapp.egg-info/entry_points.txt
tap_frontapp.egg-info/requires.txt
tap_frontapp.egg-info/top_level.txt
tap_frontapp/schemas/accounts_table.json
tap_frontapp/schemas/channels_table.json
tap_frontapp/schemas/inboxes_table.json
tap_frontapp/schemas/tags_table.json
tap_frontapp/schemas/teammates_table.json
tap_frontapp/schemas/teams_table.json